{
  "Gulpin": {
    "gen_9": {
      "gen_9": {
        "Legends: Z-A": {
          "level_up": [
            {
              "name": "Tackle",
              "type": "",
              "level": "—",
              "level_plus": "10"
            },
            {
              "name": "Smokescreen",
              "type": "",
              "level": "—",
              "level_plus": "10"
            },
            {
              "name": "Amnesia",
              "type": "",
              "level": "12",
              "level_plus": "15"
            },
            {
              "name": "Take Down",
              "type": "",
              "level": "14",
              "level_plus": "17"
            },
            {
              "name": "Acid Armor",
              "type": "",
              "level": "15",
              "level_plus": "18"
            },
            {
              "name": "Poison Jab",
              "type": "",
              "level": "17",
              "level_plus": "20"
            },
            {
              "name": "Knock Off",
              "type": "",
              "level": "20",
              "level_plus": "23"
            },
            {
              "name": "Rollout",
              "type": "",
              "level": "22",
              "level_plus": "25"
            },
            {
              "name": "Body Slam",
              "type": "",
              "level": "28",
              "level_plus": "31"
            },
            {
              "name": "Toxic",
              "type": "",
              "level": "35",
              "level_plus": "38"
            },
            {
              "name": "Sludge Bomb",
              "type": "",
              "level": "40",
              "level_plus": "43"
            },
            {
              "name": "Gunk Shot",
              "type": "",
              "level": "49",
              "level_plus": "52"
            },
            {
              "name": "Sludge Wave",
              "type": "",
              "level": "55",
              "level_plus": "58"
            },
            {
              "name": "Explosion",
              "type": "",
              "level": "60",
              "level_plus": "63"
            }
          ],
          "tm": [
            {
              "tm_id": "TM007",
              "name": "Toxic",
              "type": ""
            },
            {
              "tm_id": "TM008",
              "name": "Thunder Wave",
              "type": ""
            },
            {
              "tm_id": "TM013",
              "name": "Ice Beam",
              "type": ""
            },
            {
              "tm_id": "TM017",
              "name": "Protect",
              "type": ""
            },
            {
              "tm_id": "TM023",
              "name": "Thunder Punch",
              "type": ""
            },
            {
              "tm_id": "TM024",
              "name": "Ice Punch",
              "type": ""
            },
            {
              "tm_id": "TM029",
              "name": "Fire Punch",
              "type": ""
            },
            {
              "tm_id": "TM030",
              "name": "Swords Dance",
              "type": ""
            },
            {
              "tm_id": "TM033",
              "name": "Body Slam",
              "type": ""
            },
            {
              "tm_id": "TM035",
              "name": "Endure",
              "type": ""
            },
            {
              "tm_id": "TM040",
              "name": "Bullet Seed",
              "type": ""
            },
            {
              "tm_id": "TM041",
              "name": "Water Pulse",
              "type": ""
            },
            {
              "tm_id": "TM042",
              "name": "Giga Drain",
              "type": ""
            },
            {
              "tm_id": "TM045",
              "name": "Knock Off",
              "type": ""
            },
            {
              "tm_id": "TM046",
              "name": "Mud Shot",
              "type": ""
            },
            {
              "tm_id": "TM048",
              "name": "Self-Destruct",
              "type": ""
            },
            {
              "tm_id": "TM053",
              "name": "Sludge Bomb",
              "type": ""
            },
            {
              "tm_id": "TM064",
              "name": "Solar Beam",
              "type": ""
            },
            {
              "tm_id": "TM074",
              "name": "Shadow Ball",
              "type": ""
            },
            {
              "tm_id": "TM077",
              "name": "Poison Jab",
              "type": ""
            },
            {
              "tm_id": "TM085",
              "name": "Substitute",
              "type": ""
            },
            {
              "tm_id": "TM089",
              "name": "Toxic Spikes",
              "type": ""
            },
            {
              "tm_id": "TM091",
              "name": "Curse",
              "type": ""
            },
            {
              "tm_id": "TM100",
              "name": "Gunk Shot",
              "type": ""
            },
            {
              "tm_id": "TM109",
              "name": "Facade",
              "type": ""
            },
            {
              "tm_id": "TM111",
              "name": "Sing",
              "type": ""
            },
            {
              "tm_id": "TM112",
              "name": "Acid Spray",
              "type": ""
            },
            {
              "tm_id": "TM127",
              "name": "Dream Eater",
              "type": ""
            },
            {
              "tm_id": "TM128",
              "name": "Seed Bomb",
              "type": ""
            }
          ]
        },
        "Scarlet and Violet": {
          "level_up": [
            {
              "name": "Pound",
              "type": "",
              "level": "—"
            },
            {
              "name": "Yawn",
              "type": "",
              "level": "5"
            },
            {
              "name": "Poison Gas",
              "type": "",
              "level": "8"
            },
            {
              "name": "Sludge",
              "type": "",
              "level": "10"
            },
            {
              "name": "Amnesia",
              "type": "",
              "level": "12"
            },
            {
              "name": "Acid Spray",
              "type": "",
              "level": "17"
            },
            {
              "name": "Encore",
              "type": "",
              "level": "20"
            },
            {
              "name": "Toxic",
              "type": "",
              "level": "25"
            },
            {
              "name": "Stockpile",
              "type": "",
              "level": "28"
            },
            {
              "name": "Spit Up",
              "type": "",
              "level": "28"
            },
            {
              "name": "Swallow",
              "type": "",
              "level": "28"
            },
            {
              "name": "Sludge Bomb",
              "type": "",
              "level": "33"
            },
            {
              "name": "Gastro Acid",
              "type": "",
              "level": "36"
            },
            {
              "name": "Belch",
              "type": "",
              "level": "41"
            },
            {
              "name": "Pain Split",
              "type": "",
              "level": "44"
            },
            {
              "name": "Gunk Shot",
              "type": "",
              "level": "49"
            }
          ],
          "tm": [
            {
              "tm_id": "TM001",
              "name": "Take Down",
              "type": ""
            },
            {
              "tm_id": "TM005",
              "name": "Mud-Slap",
              "type": ""
            },
            {
              "tm_id": "TM007",
              "name": "Protect",
              "type": ""
            },
            {
              "tm_id": "TM011",
              "name": "Water Pulse",
              "type": ""
            },
            {
              "tm_id": "TM013",
              "name": "Acid Spray",
              "type": ""
            },
            {
              "tm_id": "TM018",
              "name": "Thief",
              "type": ""
            },
            {
              "tm_id": "TM025",
              "name": "Facade",
              "type": ""
            },
            {
              "tm_id": "TM035",
              "name": "Mud Shot",
              "type": ""
            },
            {
              "tm_id": "TM043",
              "name": "Fling",
              "type": ""
            },
            {
              "tm_id": "TM045",
              "name": "Venoshock",
              "type": ""
            },
            {
              "tm_id": "TM047",
              "name": "Endure",
              "type": ""
            },
            {
              "tm_id": "TM049",
              "name": "Sunny Day",
              "type": ""
            },
            {
              "tm_id": "TM050",
              "name": "Rain Dance",
              "type": ""
            },
            {
              "tm_id": "TM056",
              "name": "Bullet Seed",
              "type": ""
            },
            {
              "tm_id": "TM066",
              "name": "Body Slam",
              "type": ""
            },
            {
              "tm_id": "TM067",
              "name": "Fire Punch",
              "type": ""
            },
            {
              "tm_id": "TM068",
              "name": "Thunder Punch",
              "type": ""
            },
            {
              "tm_id": "TM069",
              "name": "Ice Punch",
              "type": ""
            },
            {
              "tm_id": "TM070",
              "name": "Sleep Talk",
              "type": ""
            },
            {
              "tm_id": "TM071",
              "name": "Seed Bomb",
              "type": ""
            },
            {
              "tm_id": "TM082",
              "name": "Thunder Wave",
              "type": ""
            },
            {
              "tm_id": "TM083",
              "name": "Poison Jab",
              "type": ""
            },
            {
              "tm_id": "TM085",
              "name": "Rest",
              "type": ""
            },
            {
              "tm_id": "TM088",
              "name": "Swords Dance",
              "type": ""
            },
            {
              "tm_id": "TM091",
              "name": "Toxic Spikes",
              "type": ""
            },
            {
              "tm_id": "TM102",
              "name": "Gunk Shot",
              "type": ""
            },
            {
              "tm_id": "TM103",
              "name": "Substitute",
              "type": ""
            },
            {
              "tm_id": "TM111",
              "name": "Giga Drain",
              "type": ""
            },
            {
              "tm_id": "TM114",
              "name": "Shadow Ball",
              "type": ""
            },
            {
              "tm_id": "TM122",
              "name": "Encore",
              "type": ""
            },
            {
              "tm_id": "TM128",
              "name": "Amnesia",
              "type": ""
            },
            {
              "tm_id": "TM130",
              "name": "Helping Hand",
              "type": ""
            },
            {
              "tm_id": "TM135",
              "name": "Ice Beam",
              "type": ""
            },
            {
              "tm_id": "TM148",
              "name": "Sludge Bomb",
              "type": ""
            },
            {
              "tm_id": "TM168",
              "name": "Solar Beam",
              "type": ""
            },
            {
              "tm_id": "TM171",
              "name": "Tera Blast",
              "type": ""
            },
            {
              "tm_id": "TM175",
              "name": "Toxic",
              "type": ""
            },
            {
              "tm_id": "TM202",
              "name": "Pain Split",
              "type": ""
            },
            {
              "tm_id": "TM214",
              "name": "Sludge Wave",
              "type": ""
            },
            {
              "tm_id": "TM224",
              "name": "Curse",
              "type": ""
            }
          ],
          "egg_moves": [
            {
              "name": "Smog",
              "type": ""
            },
            {
              "name": "Acid Armor",
              "type": ""
            },
            {
              "name": "Curse",
              "type": ""
            },
            {
              "name": "Mud-Slap",
              "type": ""
            },
            {
              "name": "Destiny Bond",
              "type": ""
            },
            {
              "name": "Clear Smog",
              "type": ""
            },
            {
              "name": "Stuff Cheeks",
              "type": ""
            }
          ]
        }
      }
    },
    "url": "https://www.serebii.net/pokedex-sv/gulpin/"
  }
}