{
  "Brilliant Diamond and Shining Pearl": {
    "level_up": [
      "Azumarill",
      "Blaziken",
      "Marill"
    ]
  },
  "Legends: Z-A": {
    "level_up": [
      "Blaziken",
      "Buneary",
      "Bunnelby",
      "Carvanha",
      "Clauncher",
      "Clawitzer",
      "Cobalion",
      "Combusken",
      "Dachsbun",
      "Diggersby",
      "Fidough",
      "Froakie",
      "Frogadier",
      "Greninja",
      "Grumpig",
      "Gyarados",
      "Hawlucha",
      "Keldeo Ordinary Form",
      "Lopunny",
      "Mabosstiff",
      "Maschiff",
      "Sharpedo",
      "Spoink",
      "Stunfisk",
      "Stunfisk Galarian Stunfisk",
      "Torchic",
      "Virizion"
    ]
  },
  "Scarlet and Violet": {
    "egg_moves": [
      "Aipom",
      "Alomomola",
      "Ambipom",
      "Finizen",
      "Palafin Zero Form"
    ],
    "level_up": [
      "Azumarill",
      "Azurill",
      "Blaziken",
      "Cetitan",
      "Cetoddle",
      "Chi-Yu",
      "Cinderace",
      "Clauncher",
      "Clawitzer",
      "Combusken",
      "Finneon",
      "Froakie",
      "Frogadier",
      "Grumpig",
      "Hawlucha",
      "Hoppip",
      "Jumpluff",
      "Lokix",
      "Lumineon",
      "Marill",
      "Mienfoo",
      "Mienshao",
      "Politoed",
      "Raboot",
      "Scorbunny",
      "Skiploom",
      "Spoink",
      "Torchic"
    ]
  },
  "Sword and Shield": {
    "egg_moves": [
      "Aipom",
      "Ambipom"
    ],
    "level_up": [
      "Azumarill",
      "Azurill",
      "Blaziken",
      "Buneary",
      "Bunnelby",
      "Cinderace",
      "Clauncher",
      "Clawitzer",
      "Combusken",
      "Diggersby",
      "Finneon",
      "Grumpig",
      "Hawlucha",
      "Hoppip",
      "Jumpluff",
      "Lopunny",
      "Lumineon",
      "Mantine",
      "Mantyke",
      "Marill",
      "Mienfoo",
      "Mienshao",
      "Pheromosa",
      "Politoed",
      "Raboot",
      "Scorbunny",
      "Skiploom",
      "Spoink",
      "Stunfisk",
      "Stunfisk Galarian Stunfisk",
      "Torchic",
      "Wailmer",
      "Wailord"
    ],
    "tm": [
      "Absol",
      "Absol Mega Absol",
      "Archen",
      "Archeops",
      "Arrokuda",
      "Azumarill",
      "Azurill",
      "Barboach",
      "Barraskewda",
      "Basculin Blue-Striped Form",
      "Basculin Red-Striped Form",
      "Basculin White-Striped Form",
      "Blaziken",
      "Blaziken Mega Blaziken",
      "Bounsweet",
      "Buneary",
      "Bunnelby",
      "Buzzwole",
      "Carvanha",
      "Chinchou",
      "Cinderace",
      "Clauncher",
      "Clawitzer",
      "Clefable",
      "Clefairy",
      "Cobalion",
      "Combusken",
      "Croagunk",
      "Delibird",
      "Diggersby",
      "Dragalge",
      "Drizzile",
      "Dubwool",
      "Galvantula",
      "Goldeen",
      "Gyarados",
      "Gyarados Mega Gyarados",
      "Hawlucha",
      "Hawlucha Mega Hawlucha",
      "Hitmonlee",
      "Horsea",
      "Igglybuff",
      "Inteleon",
      "Jigglypuff",
      "Joltik",
      "Keldeo Ordinary Form",
      "Keldeo Resolute Form",
      "Kingdra",
      "Lanturn",
      "Lopunny",
      "Lopunny Mega Lopunny",
      "Magikarp",
      "Mantine",
      "Mantyke",
      "Maractus",
      "Marill",
      "Marshadow",
      "Mew",
      "Mienfoo",
      "Mienshao",
      "Octillery",
      "Palpitoad",
      "Pheromosa",
      "Politoed",
      "Ponyta Galarian Ponyta",
      "Qwilfish",
      "Qwilfish Hisuian Qwilfish",
      "Raboot",
      "Rapidash Galarian Rapidash",
      "Regieleki",
      "Relicanth",
      "Remoraid",
      "Scorbunny",
      "Seadra",
      "Seaking",
      "Seismitoad",
      "Sharpedo",
      "Sharpedo Mega Sharpedo",
      "Shiftry",
      "Skrelp",
      "Sobble",
      "Steenee",
      "Stunfisk Galarian Stunfisk",
      "Togedemaru",
      "Torchic",
      "Toxicroak",
      "Tsareena",
      "Tympole",
      "Victini",
      "Virizion",
      "Wailmer",
      "Wailord",
      "Whiscash",
      "Wigglytuff",
      "Zapdos Galarian Zapdos",
      "Zeraora",
      "Zoroark",
      "Zoroark Hisuian Zoroark",
      "Zorua",
      "Zorua Hisuian Zorua"
    ]
  }
}